pyview/__init__.py
pyview/assets/js/app.js
pyview/assets/js/uploaders.js
pyview/assets/package-lock.json
pyview/assets/package.json
pyview/async_stream_runner.py
pyview/auth/__init__.py
pyview/auth/provider.py
pyview/auth/required.py
pyview/binding/__init__.py
pyview/binding/binder.py
pyview/binding/context.py
pyview/binding/converters.py
pyview/binding/helpers.py
pyview/binding/injectables.py
pyview/binding/params.py
pyview/binding/result.py
pyview/changesets/__init__.py
pyview/changesets/changesets.py
pyview/cli/__init__.py
pyview/cli/commands/__init__.py
pyview/cli/commands/create_view.py
pyview/cli/main.py
pyview/components/__init__.py
pyview/components/base.py
pyview/components/lifecycle.py
pyview/components/manager.py
pyview/components/renderer.py
pyview/components/slots.py
pyview/csrf.py
pyview/events/AutoEventDispatch.py
pyview/events/BaseEventHandler.py
pyview/events/__init__.py
pyview/events/info_event.py
pyview/instrumentation/__init__.py
pyview/instrumentation/interfaces.py
pyview/instrumentation/noop.py
pyview/js.py
pyview/live_routes.py
pyview/live_socket.py
pyview/live_view.py
pyview/meta.py
pyview/phx_message.py
pyview/playground/__init__.py
pyview/playground/builder.py
pyview/playground/favicon.py
pyview/pyview.py
pyview/secret.py
pyview/session.py
pyview/static/assets/app.js
pyview/static/assets/uploaders.js
pyview/stream.py
pyview/template/__init__.py
pyview/template/context_processor.py
pyview/template/live_template.py
pyview/template/live_view_template.py
pyview/template/render_diff.py
pyview/template/root_template.py
pyview/template/serializer.py
pyview/template/template_view.py
pyview/template/utils.py
pyview/uploads.py
pyview/vendor/__init__.py
pyview/vendor/flet/pubsub/__init__.py
pyview/vendor/flet/pubsub/pub_sub.py
pyview/vendor/ibis/__init__.py
pyview/vendor/ibis/compiler.py
pyview/vendor/ibis/context.py
pyview/vendor/ibis/errors.py
pyview/vendor/ibis/filters.py
pyview/vendor/ibis/loaders.py
pyview/vendor/ibis/nodes.py
pyview_web-0.8.1.dist-info/WHEEL
pyview_web-0.8.1.dist-info/entry_points.txt
pyview_web-0.8.1.dist-info/METADATA
pyview_web-0.8.1.dist-info/RECORD
