Metadata-Version: 2.3
Name: pyview-web
Version: 0.8.1
Summary: LiveView in Python
Keywords: web,api,LiveView
Author: Larry Ogrodnek
Author-email: Larry Ogrodnek <ogrodnek@gmail.com>
License: MIT
Classifier: Intended Audience :: Information Technology
Classifier: Intended Audience :: System Administrators
Classifier: Operating System :: OS Independent
Classifier: Programming Language :: Python :: 3
Classifier: Programming Language :: Python
Classifier: Topic :: Internet
Classifier: Topic :: Software Development :: Libraries :: Application Frameworks
Classifier: Topic :: Software Development :: Libraries :: Python Modules
Classifier: Topic :: Software Development :: Libraries
Classifier: Topic :: Software Development
Classifier: Typing :: Typed
Classifier: Development Status :: 4 - Beta
Classifier: Environment :: Web Environment
Classifier: Framework :: AsyncIO
Classifier: Framework :: Pydantic
Classifier: Intended Audience :: Developers
Classifier: License :: OSI Approved :: MIT License
Classifier: Programming Language :: Python :: 3 :: Only
Classifier: Programming Language :: Python :: 3.11
Classifier: Programming Language :: Python :: 3.12
Classifier: Programming Language :: Python :: 3.13
Classifier: Programming Language :: Python :: 3.14
Classifier: Topic :: Internet :: WWW/HTTP :: HTTP Servers
Classifier: Topic :: Internet :: WWW/HTTP
Requires-Dist: starlette>=0.50.0,<0.51
Requires-Dist: wsproto>=1.3.0,<2
Requires-Dist: apscheduler>=3.11.0,<4
Requires-Dist: markupsafe>=3.0.2,<4
Requires-Dist: itsdangerous>=2.2.0,<3
Requires-Dist: pydantic>=2.11,<3
Requires-Dist: click>=8.1.7,<9
Requires-Python: >=3.11, <3.15
Project-URL: Homepage, https://pyview.rocks
Project-URL: Repository, https://github.com/ogrodnek/pyview
